chanjo_report/__init__.py
chanjo_report/cli/__init__.py
chanjo_report/cli/core.py
chanjo_report/cli/utils.py
chanjo_report/interfaces/__init__.py
chanjo_report/interfaces/html.py
chanjo_report/interfaces/pdf.py
chanjo_report/server/__init__.py
chanjo_report/server/app.py
chanjo_report/server/config.py
chanjo_report/server/constants.py
chanjo_report/server/extensions.py
chanjo_report/server/utils.py
chanjo_report/server/blueprints/__init__.py
chanjo_report/server/blueprints/index/__init__.py
chanjo_report/server/blueprints/index/views.py
chanjo_report/server/blueprints/report/__init__.py
chanjo_report/server/blueprints/report/controllers.py
chanjo_report/server/blueprints/report/utils.py
chanjo_report/server/blueprints/report/views.py
chanjo_report/server/blueprints/report/static/main.css
chanjo_report/server/blueprints/report/templates/report/gene.html
chanjo_report/server/blueprints/report/templates/report/genes.html
chanjo_report/server/blueprints/report/templates/report/report.html
chanjo_report/server/blueprints/report/templates/report/layouts/base.html
chanjo_report/server/translations/sv/LC_MESSAGES/messages.po
chanjo_report-4.11.5.dist-info/licenses/AUTHORS
chanjo_report-4.11.5.dist-info/licenses/LICENSE
chanjo_report-4.11.5.dist-info/METADATA
chanjo_report-4.11.5.dist-info/WHEEL
chanjo_report-4.11.5.dist-info/entry_points.txt
chanjo_report-4.11.5.dist-info/top_level.txt
chanjo_report-4.11.5.dist-info/RECORD
