Metadata-Version: 2.4
Name: chanjo-report
Version: 4.11.5
Summary: Automatically render coverage reports from Chanjo ouput
Home-page: https://github.com/robinandeer/chanjo-report
Author: Robin Andeer
Author-email: robin.andeer@scilifelab.se
License: MIT
Keywords: chanjo-report development
Classifier: Development Status :: 3 - Alpha
Classifier: Intended Audience :: Developers
Classifier: Topic :: Software Development
Classifier: License :: OSI Approved :: MIT License
Classifier: Programming Language :: Python :: 3.6
Classifier: Environment :: Console
License-File: LICENSE
License-File: AUTHORS
Requires-Dist: cairocffi
Requires-Dist: chanjo>=4.7.2
Requires-Dist: cffi
Requires-Dist: cryptography
Requires-Dist: Flask
Requires-Dist: Flask-Babel>=3
Requires-Dist: Flask-DebugToolbar
Requires-Dist: Flask-WeasyPrint
Requires-Dist: importlib_resources
Requires-Dist: lxml>=3.0
Requires-Dist: path.py
Requires-Dist: pymysql
Requires-Dist: pyscss
Requires-Dist: six
Requires-Dist: Flask-SQLAlchemy
Requires-Dist: tabulate
Requires-Dist: toml
Requires-Dist: toolz
Dynamic: author
Dynamic: author-email
Dynamic: classifier
Dynamic: description
Dynamic: description-content-type
Dynamic: home-page
Dynamic: keywords
Dynamic: license
Dynamic: license-file
Dynamic: requires-dist
Dynamic: summary
